{
  "stock":
          [
            {"id": 1,
              "department_id": 1,
              "name": "KalanCO",
              "short_name": "KNCO",
              "cost": 200,
              "lowest_cost": 20},

            {"id": 2,
              "department_id": 2,
              "name": "United Aerospace Corporation",
              "short_name": "UAC",
              "cost": 300,
              "lowest_cost": 30},

            {"id": 3,
              "department_id": 3,
              "name": "MetIndustries",
              "short_name": "MTI",
              "cost": 100,
              "lowest_cost": 10},

            {"id": 4,
              "department_id": 4,
              "name": "NiccoDixit",
              "short_name": "NDXT",
              "cost": 400,
              "lowest_cost": 40},

            {"id": 5,
              "department_id": 5,
              "name": "Union of Soviet Socialist Gastronomes",
              "short_name": "USSG",
              "cost": 300,
              "lowest_cost": 30},

            {"id": 6,
              "department_id": 6,
              "name": "Concordance Extraction Corporation",
              "short_name": "CEC",
              "cost": 550,
              "lowest_cost": 55},

            {"id": 7,
              "department_id": 7,
              "name": "Yeniseimetal Forces",
              "short_name": "YMF",
              "cost": 330,
              "lowest_cost": 33},

            {"id": 8,
              "department_id": 8,
              "name": "OUnity Games",
              "short_name": "OUG",
              "cost": 340,
              "lowest_cost": 34},

            {"id": 9,
              "department_id": 9,
              "name": "Nuclear Fusion Control Systems",
              "short_name": "NFCS",
              "cost": 220,
              "lowest_cost": 22}
          ]
}